mailchimp.py
mailchimp-2.0.10.dist-info/LICENSE
mailchimp-2.0.10.dist-info/METADATA
mailchimp-2.0.10.dist-info/WHEEL
mailchimp-2.0.10.dist-info/top_level.txt
mailchimp-2.0.10.dist-info/RECORD
