Metadata-Version: 2.1
Name: mailchimp
Version: 2.0.10
Summary: Deprecated. Replaced by mailchimp-marketing - A CLI client and Python API library for the MailChimp email platform.
Home-page: https://bitbucket.org/mailchimp/mailchimp-api-python/
Author: MailChimp Devs
Author-email: api@mailchimp.com
License: MIT
Keywords: mailchimp email api
Platform: UNKNOWN
Classifier: Development Status :: 7 - Inactive
Classifier: Environment :: Console
Classifier: Intended Audience :: Developers
Classifier: License :: OSI Approved :: MIT License
Classifier: Topic :: Communications :: Email
Classifier: Programming Language :: Python
Classifier: Programming Language :: Python :: 2
Classifier: Programming Language :: Python :: 3
Requires-Dist: requests (>=0.13.2)
Requires-Dist: docopt (==0.4.0)
